{
  "SYSTEM_CONSTANTS": {
    "MAX_SP": 300,
    "SP_REGEN_PER_SEC": 8,
    "SKILL_SP_COST_DEFAULT": 100
  },
  "ICON_DATABASE": {
    "break": "/Endaxis/icons/break.png",
    "armor_break": "/Endaxis/icons/armor_break.png",
    "stagger": "/Endaxis/icons/stagger.png",
    "knockdown": "/Endaxis/icons/knockdown.png",
    "knockup": "/Endaxis/icons/knockup.png",
    "blaze_attach": "/Endaxis/icons/blaze_attach.png",
    "emag_attach": "/Endaxis/icons/emag_attach.png",
    "cold_attach": "/Endaxis/icons/cold_attach.png",
    "nature_attach": "/Endaxis/icons/nature_attach.png",
    "blaze_burst": "/Endaxis/icons/blaze_burst.png",
    "emag_burst": "/Endaxis/icons/emag_burst.png",
    "cold_burst": "/Endaxis/icons/cold_burst.png",
    "nature_burst": "/Endaxis/icons/nature_burst.png",
    "burning": "/Endaxis/icons/burning.png",
    "conductive": "/Endaxis/icons/conductive.png",
    "frozen": "/Endaxis/icons/frozen.png",
    "ice_shatter": "/Endaxis/icons/ice_shatter.png",
    "corrosion": "/Endaxis/icons/corrosion.png",
    "default": "/Endaxis/icons/default_icon.png"
  },
  "characterRoster": [
    {
      "id": "ENDMINISTRATOR",
      "name": "管理员",
      "rarity": 6,
      "element": "physical",
      "avatar": "/Endaxis/avatars/ENDMINISTRATOR.png",
      "exclusive_buffs": [
        {
          "key": "crystallization",
          "name": "结晶",
          "path": "/Endaxis/icons/crystallization.png"
        }
      ],
      "attack_duration": 3.7,
      "attack_spGain": 20,
      "attack_allowed_types": [
        "break",
        "armor_break",
        "ice_shatter",
        "stagger",
        "knockdown",
        "knockup",
        "nature_attach",
        "corrosion",
        "nature_burst",
        "cold_attach",
        "frozen",
        "cold_burst",
        "emag_attach",
        "conductive",
        "emag_burst",
        "blaze_burst",
        "burning",
        "blaze_attach",
        "default"
      ],
      "attack_anomalies": [],
      "skill_duration": 0.8,
      "skill_spCost": 100,
      "skill_gaugeGain": 16,
      "skill_allowed_types": [
        "stagger",
        "break",
        "ice_shatter"
      ],
      "skill_anomalies": [
        [
          {
            "type": "stagger",
            "stacks": "",
            "duration": ""
          }
        ]
      ],
      "link_duration": 1.2,
      "link_cooldown": 16,
      "link_spGain": 0,
      "link_gaugeGain": 10,
      "link_allowed_types": [
        "crystallization"
      ],
      "link_anomalies": [
        [
          {
            "type": "crystallization",
            "stacks": 1,
            "duration": 4
          }
        ]
      ],
      "ultimate_duration": 0.5,
      "ultimate_gaugeMax": 80,
      "ultimate_gaugeReply": 0,
      "ultimate_allowed_types": [
        "default"
      ],
      "ultimate_anomalies": [],
      "execution_duration": 1.5,
      "execution_spGain": 20,
      "execution_allowed_types": [
        "default",
        "conductive",
        "emag_attach",
        "emag_burst",
        "blaze_burst",
        "burning",
        "blaze_attach",
        "knockup",
        "break",
        "ice_shatter",
        "nature_attach",
        "corrosion",
        "nature_burst",
        "knockdown",
        "cold_attach",
        "frozen",
        "cold_burst",
        "stagger",
        "armor_break"
      ],
      "execution_anomalies": [],
      "skill_spGain": 0,
      "ultimate_spGain": 0,
      "skill_teamGaugeGain": 8,
      "link_stagger": 10,
      "accept_team_gauge": true,
      "skill_anomaly_delays": [
        0.5
      ],
      "attack_stagger": 18,
      "link_anomaly_delays": [
        0.8
      ],
      "variants": [
        {
          "id": "v_1764438597352",
          "name": "强化连携",
          "type": "link",
          "duration": 1.2,
          "stagger": 16,
          "spGain": 0,
          "allowedTypes": [
            "crystallization"
          ],
          "physicalAnomaly": [
            [
              {
                "type": "crystallization",
                "stacks": 1,
                "duration": 4
              }
            ]
          ],
          "anomalyRowDelays": [
            0.8
          ],
          "cooldown": 16,
          "gaugeGain": 0
        }
      ],
      "skill_stagger": 10,
      "ultimate_stagger": 25
    },
    {
      "id": "POGRANICHNK",
      "name": "骏卫",
      "rarity": 6,
      "element": "physical",
      "avatar": "/Endaxis/avatars/POGRANICHNK.png",
      "exclusive_buffs": [
        {
          "key": "steel_oath",
          "name": "铁誓",
          "path": "/Endaxis/icons/steel_oath.png"
        }
      ],
      "attack_duration": 3.3,
      "attack_spGain": 20,
      "attack_allowed_types": [
        "armor_break",
        "break",
        "ice_shatter",
        "stagger",
        "knockdown",
        "knockup",
        "blaze_burst",
        "burning",
        "blaze_attach",
        "nature_attach",
        "corrosion",
        "nature_burst",
        "cold_attach",
        "frozen",
        "cold_burst",
        "emag_attach",
        "conductive",
        "emag_burst",
        "default"
      ],
      "attack_anomalies": [],
      "skill_duration": 1.7,
      "skill_spCost": 100,
      "skill_gaugeGain": 0,
      "skill_allowed_types": [
        "armor_break",
        "break",
        "ice_shatter"
      ],
      "skill_anomalies": [
        [
          {
            "type": "armor_break",
            "stacks": 1,
            "duration": 0,
            "sp": 5,
            "stagger": 10
          },
          {
            "type": "armor_break",
            "stacks": 2,
            "duration": 0,
            "sp": 10,
            "stagger": 0
          },
          {
            "type": "armor_break",
            "stacks": 3,
            "duration": 0,
            "sp": 20,
            "stagger": 0
          },
          {
            "type": "armor_break",
            "stacks": 4,
            "duration": 0,
            "sp": 30,
            "stagger": 0
          }
        ]
      ],
      "link_duration": 2.7,
      "link_cooldown": 18,
      "link_spGain": 0,
      "link_gaugeGain": 10,
      "link_allowed_types": [
        "default"
      ],
      "link_anomalies": [
        [
          {
            "type": "default",
            "stacks": 1,
            "duration": 0.6,
            "stagger": 3,
            "sp": 5
          },
          {
            "type": "default",
            "stacks": 1,
            "duration": 0.9,
            "sp": 7,
            "stagger": 3
          },
          {
            "type": "default",
            "stacks": 1,
            "duration": 0,
            "stagger": 4,
            "sp": 13
          }
        ]
      ],
      "ultimate_duration": 0.5,
      "ultimate_gaugeMax": 90,
      "ultimate_gaugeReply": 0,
      "ultimate_allowed_types": [
        "steel_oath"
      ],
      "ultimate_anomalies": [
        [
          {
            "type": "steel_oath",
            "stacks": 5,
            "duration": 0,
            "sp": 0,
            "stagger": 10
          },
          {
            "type": "steel_oath",
            "stacks": 4,
            "duration": 0,
            "sp": 7.5,
            "stagger": 0
          },
          {
            "type": "steel_oath",
            "stacks": 3,
            "duration": 0,
            "sp": 7.5,
            "stagger": 0
          },
          {
            "type": "steel_oath",
            "stacks": 2,
            "duration": 0,
            "sp": 7.5,
            "stagger": 0
          },
          {
            "type": "steel_oath",
            "stacks": 1,
            "duration": 0,
            "sp": 30,
            "stagger": 15
          }
        ]
      ],
      "execution_duration": 1.5,
      "execution_spGain": 20,
      "execution_allowed_types": [
        "burning",
        "blaze_attach",
        "blaze_burst",
        "default",
        "nature_attach",
        "corrosion",
        "nature_burst",
        "knockup",
        "break",
        "ice_shatter",
        "knockdown",
        "cold_attach",
        "frozen",
        "cold_burst",
        "stagger",
        "armor_break",
        "emag_attach",
        "conductive",
        "emag_burst"
      ],
      "execution_anomalies": [],
      "skill_spGain": 0,
      "ultimate_spGain": 0,
      "skill_teamGaugeGain": 6,
      "accept_team_gauge": true,
      "skill_anomaly_delays": [
        1.5
      ],
      "link_anomaly_delays": [
        0.7
      ],
      "attack_stagger": 18,
      "variants": [
        {
          "id": "POGRANICHNK_link3",
          "name": "强化连携",
          "type": "link",
          "duration": 2.7,
          "stagger": 0,
          "spGain": 0,
          "allowedTypes": [
            "default"
          ],
          "physicalAnomaly": [
            [
              {
                "type": "default",
                "stacks": 1,
                "duration": 0.6,
                "stagger": 3,
                "sp": 5
              },
              {
                "type": "default",
                "stacks": 1,
                "duration": 0.9,
                "sp": 7,
                "stagger": 3
              },
              {
                "type": "default",
                "stacks": 1,
                "duration": 0,
                "stagger": 4,
                "sp": 13
              }
            ]
          ],
          "anomalyRowDelays": [
            0.7
          ],
          "cooldown": 18,
          "gaugeGain": 10
        },
        {
          "id": "POGRANICHNK_link1",
          "name": "一层连携",
          "type": "link",
          "duration": 2.7,
          "stagger": 0,
          "spGain": 0,
          "allowedTypes": [
            "default"
          ],
          "physicalAnomaly": [
            [
              {
                "type": "default",
                "stacks": 1,
                "duration": 0,
                "stagger": 3,
                "sp": 5
              }
            ]
          ],
          "anomalyRowDelays": [
            0.7
          ],
          "cooldown": 18,
          "gaugeGain": 10
        },
        {
          "id": "POGRANICHNK_link2",
          "name": "二层连携",
          "type": "link",
          "duration": 2.7,
          "stagger": 0,
          "spGain": 0,
          "allowedTypes": [
            "default"
          ],
          "physicalAnomaly": [
            [
              {
                "type": "default",
                "stacks": 1,
                "duration": 0.6,
                "stagger": 3,
                "sp": 5
              },
              {
                "type": "default",
                "stacks": 1,
                "duration": 0,
                "sp": 7,
                "stagger": 3
              }
            ]
          ],
          "anomalyRowDelays": [
            0.7
          ],
          "cooldown": 18,
          "gaugeGain": 10
        }
      ],
      "link_stagger": 0,
      "ultimate_stagger": 0,
      "ultimate_anomaly_delays": [
        0.5
      ],
      "skill_stagger": 0
    },
    {
      "id": "ARDELIA",
      "name": "艾尔黛拉",
      "rarity": 6,
      "element": "nature",
      "avatar": "/Endaxis/avatars/ARDELIA.png",
      "exclusive_buffs": [
        {
          "key": "physical_weakness",
          "name": "物理易伤",
          "path": "/Endaxis/icons/physical_weakness.png"
        },
        {
          "key": "magic_weakness",
          "name": "法术易伤",
          "path": "/Endaxis/icons/magic_weakness.png"
        }
      ],
      "attack_duration": 4.3,
      "attack_spGain": 15,
      "attack_allowed_types": [
        "knockup",
        "break",
        "ice_shatter",
        "knockdown",
        "stagger",
        "armor_break",
        "emag_attach",
        "conductive",
        "emag_burst",
        "cold_attach",
        "frozen",
        "cold_burst",
        "nature_attach",
        "corrosion",
        "nature_burst",
        "blaze_burst",
        "burning",
        "blaze_attach",
        "default"
      ],
      "attack_anomalies": [],
      "skill_duration": 1.3,
      "skill_spCost": 100,
      "skill_gaugeGain": 0,
      "skill_allowed_types": [
        "physical_weakness",
        "magic_weakness"
      ],
      "skill_anomalies": [
        [
          {
            "type": "physical_weakness",
            "stacks": 1,
            "duration": 0
          },
          {
            "type": "magic_weakness",
            "stacks": 1,
            "duration": 0
          }
        ]
      ],
      "link_duration": 1.2,
      "link_cooldown": 18,
      "link_spGain": 0,
      "link_gaugeGain": 0,
      "link_allowed_types": [
        "corrosion",
        "nature_attach",
        "nature_burst"
      ],
      "link_anomalies": [
        [
          {
            "type": "corrosion",
            "stacks": 1,
            "duration": 10
          }
        ]
      ],
      "ultimate_duration": 0.5,
      "ultimate_gaugeMax": 90,
      "ultimate_gaugeReply": 0,
      "ultimate_allowed_types": [
        "default"
      ],
      "ultimate_anomalies": [],
      "execution_duration": 1.5,
      "execution_spGain": 20,
      "execution_allowed_types": [
        "conductive",
        "emag_attach",
        "emag_burst",
        "default",
        "corrosion",
        "nature_attach",
        "nature_burst",
        "burning",
        "blaze_attach",
        "blaze_burst",
        "knockup",
        "break",
        "ice_shatter",
        "knockdown",
        "cold_attach",
        "frozen",
        "cold_burst",
        "stagger",
        "armor_break"
      ],
      "execution_anomalies": [],
      "skill_spGain": 0,
      "ultimate_spGain": 0,
      "skill_teamGaugeGain": 6,
      "accept_team_gauge": true,
      "attack_stagger": 18,
      "skill_anomaly_delays": [
        1
      ],
      "link_anomaly_delays": [
        2.6
      ]
    },
    {
      "id": "LASTRITE",
      "name": "别礼",
      "rarity": 6,
      "element": "cold",
      "avatar": "/Endaxis/avatars/LASTRITE.png",
      "exclusive_buffs": [
        {
          "key": "cold_enchantment",
          "name": "寒冷附魔",
          "path": "/Endaxis/icons/cold_enchantment.png"
        }
      ],
      "attack_duration": 4.3,
      "attack_spGain": 20,
      "attack_allowed_types": [
        "default",
        "conductive",
        "emag_attach",
        "emag_burst",
        "blaze_burst",
        "burning",
        "blaze_attach",
        "knockup",
        "break",
        "ice_shatter",
        "knockdown",
        "nature_attach",
        "corrosion",
        "nature_burst",
        "stagger",
        "armor_break",
        "cold_attach",
        "frozen",
        "cold_burst"
      ],
      "attack_anomalies": [],
      "skill_duration": 0.5,
      "skill_spCost": 100,
      "skill_gaugeGain": 0,
      "skill_allowed_types": [
        "cold_enchantment"
      ],
      "skill_anomalies": [
        [
          {
            "type": "cold_enchantment",
            "stacks": 1,
            "duration": 0
          }
        ]
      ],
      "link_duration": 0.8,
      "link_cooldown": 9,
      "link_spGain": 0,
      "link_gaugeGain": 0,
      "link_allowed_types": [
        "default"
      ],
      "link_anomalies": [],
      "ultimate_duration": 0.5,
      "ultimate_gaugeMax": 100,
      "ultimate_gaugeReply": 0,
      "ultimate_allowed_types": [
        "default"
      ],
      "ultimate_anomalies": [],
      "execution_duration": 1.5,
      "execution_spGain": 20,
      "execution_allowed_types": [
        "default",
        "burning",
        "blaze_attach",
        "blaze_burst",
        "conductive",
        "emag_attach",
        "emag_burst",
        "nature_attach",
        "corrosion",
        "nature_burst",
        "knockdown",
        "break",
        "ice_shatter",
        "knockup",
        "stagger",
        "cold_attach",
        "frozen",
        "cold_burst",
        "armor_break"
      ],
      "execution_anomalies": [],
      "skill_spGain": "",
      "ultimate_spGain": 0,
      "skill_teamGaugeGain": 6,
      "accept_team_gauge": false,
      "attack_stagger": 25
    },
    {
      "id": "GILBERTA",
      "name": "洁尔佩塔",
      "rarity": 6,
      "element": "nature",
      "avatar": "/Endaxis/avatars/GILBERTA.png",
      "exclusive_buffs": [
        {
          "key": "slow",
          "name": "减速",
          "path": "/Endaxis/icons/slow.png"
        },
        {
          "key": "magic_weakness",
          "name": "法术易伤",
          "path": "/Endaxis/icons/magic_weakness.png"
        }
      ],
      "attack_duration": 3.5,
      "attack_spGain": 15,
      "attack_allowed_types": [
        "break",
        "armor_break",
        "stagger",
        "knockdown",
        "knockup",
        "blaze_attach",
        "emag_attach",
        "cold_attach",
        "nature_attach",
        "blaze_burst",
        "emag_burst",
        "cold_burst",
        "nature_burst",
        "burning",
        "conductive",
        "frozen",
        "ice_shatter",
        "corrosion",
        "default"
      ],
      "attack_anomalies": [],
      "skill_duration": 4,
      "skill_spCost": 100,
      "skill_spGain": 0,
      "skill_gaugeGain": 0,
      "skill_teamGaugeGain": 6,
      "skill_allowed_types": [
        "corrosion",
        "nature_attach",
        "nature_burst"
      ],
      "skill_anomalies": [
        [
          {
            "type": "nature_attach",
            "stacks": 1,
            "duration": 0
          }
        ]
      ],
      "link_duration": 2,
      "link_cooldown": 20,
      "link_spGain": 0,
      "link_gaugeGain": 0,
      "link_allowed_types": [
        "knockup",
        "break",
        "ice_shatter"
      ],
      "link_anomalies": [
        [
          {
            "type": "knockup",
            "stacks": 1,
            "duration": 0
          }
        ]
      ],
      "ultimate_duration": 0.5,
      "ultimate_gaugeMax": 90,
      "ultimate_spGain": 0,
      "ultimate_gaugeReply": 0,
      "ultimate_allowed_types": [
        "slow",
        "magic_weakness",
        "knockup",
        "break",
        "ice_shatter",
        "nature_attach",
        "corrosion",
        "nature_burst"
      ],
      "ultimate_anomalies": [
        [
          {
            "type": "slow",
            "stacks": 1,
            "duration": 0
          },
          {
            "type": "magic_weakness",
            "stacks": 1,
            "duration": 0
          },
          {
            "type": "nature_attach",
            "stacks": 1,
            "duration": 0
          }
        ]
      ],
      "execution_duration": 1.5,
      "execution_spGain": 20,
      "execution_allowed_types": [
        "default",
        "conductive",
        "emag_attach",
        "emag_burst",
        "blaze_burst",
        "burning",
        "blaze_attach",
        "knockup",
        "break",
        "ice_shatter",
        "nature_attach",
        "corrosion",
        "nature_burst",
        "knockdown",
        "cold_attach",
        "frozen",
        "cold_burst",
        "stagger",
        "armor_break"
      ],
      "execution_anomalies": [],
      "accept_team_gauge": true,
      "attack_stagger": 16,
      "skill_anomaly_delays": [
        3.6
      ],
      "link_anomaly_delays": [
        1.6
      ],
      "ultimate_anomaly_delays": [
        0
      ]
    },
    {
      "id": "YVONNE",
      "name": "伊冯",
      "rarity": 6,
      "element": "cold",
      "avatar": "/Endaxis/avatars/YVONNE.png",
      "exclusive_buffs": [],
      "attack_duration": 3.7,
      "attack_spGain": 15,
      "attack_allowed_types": [
        "break",
        "armor_break",
        "stagger",
        "knockdown",
        "knockup",
        "blaze_attach",
        "emag_attach",
        "cold_attach",
        "nature_attach",
        "blaze_burst",
        "emag_burst",
        "cold_burst",
        "nature_burst",
        "burning",
        "conductive",
        "frozen",
        "ice_shatter",
        "corrosion",
        "default"
      ],
      "attack_anomalies": [],
      "skill_duration": 1.3,
      "skill_spCost": 100,
      "skill_spGain": 0,
      "skill_gaugeGain": 0,
      "skill_teamGaugeGain": 6,
      "skill_allowed_types": [
        "frozen",
        "cold_attach",
        "cold_burst"
      ],
      "skill_anomalies": [
        [
          {
            "type": "cold_attach",
            "stacks": 1,
            "duration": 0
          }
        ]
      ],
      "link_duration": 1.1,
      "link_cooldown": 22,
      "link_spGain": 0,
      "link_gaugeGain": 0,
      "link_allowed_types": [
        "cold_burst",
        "frozen",
        "cold_attach"
      ],
      "link_anomalies": [
        [
          {
            "type": "cold_attach",
            "stacks": 1,
            "duration": 0
          }
        ]
      ],
      "ultimate_duration": 0.5,
      "ultimate_gaugeMax": 200,
      "ultimate_spGain": 0,
      "ultimate_gaugeReply": 0,
      "ultimate_allowed_types": [
        "frozen",
        "cold_attach",
        "cold_burst"
      ],
      "ultimate_anomalies": [
        [
          {
            "type": "cold_attach",
            "stacks": 1,
            "duration": 0
          }
        ]
      ],
      "execution_duration": 1.5,
      "execution_spGain": 20,
      "execution_allowed_types": [
        "default",
        "burning",
        "blaze_attach",
        "blaze_burst",
        "conductive",
        "emag_attach",
        "emag_burst",
        "nature_attach",
        "corrosion",
        "nature_burst",
        "knockup",
        "break",
        "ice_shatter",
        "knockdown",
        "cold_attach",
        "frozen",
        "cold_burst",
        "stagger",
        "armor_break"
      ],
      "execution_anomalies": [],
      "accept_team_gauge": true,
      "attack_stagger": 17,
      "skill_anomaly_delays": [
        1
      ],
      "link_anomaly_delays": [
        4.2
      ],
      "ultimate_anomaly_delays": [
        12
      ]
    },
    {
      "id": "LAEVATAIN",
      "name": "莱万汀",
      "rarity": 6,
      "element": "blaze",
      "avatar": "/Endaxis/avatars/LAEVATAIN.png",
      "exclusive_buffs": [
        {
          "key": "magma_1",
          "name": "熔火1",
          "path": "/Endaxis/icons/magma_1.png"
        },
        {
          "key": "magma_2",
          "name": "熔火2",
          "path": "/Endaxis/icons/magma_2.png"
        },
        {
          "key": "magma_3",
          "name": "熔火3",
          "path": "/Endaxis/icons/magma_3.png"
        },
        {
          "key": "magma_4",
          "name": "熔火4",
          "path": "/Endaxis/icons/magma_4.png"
        }
      ],
      "attack_duration": 3.3,
      "attack_spGain": 15,
      "attack_allowed_types": [
        "magma_1",
        "magma_2",
        "magma_3",
        "magma_4",
        "break",
        "armor_break",
        "stagger",
        "knockdown",
        "knockup",
        "blaze_attach",
        "emag_attach",
        "cold_attach",
        "nature_attach",
        "blaze_burst",
        "emag_burst",
        "cold_burst",
        "nature_burst",
        "burning",
        "conductive",
        "frozen",
        "ice_shatter",
        "corrosion",
        "default"
      ],
      "attack_anomalies": [],
      "skill_duration": 1,
      "skill_spCost": 100,
      "skill_spGain": 0,
      "skill_gaugeGain": 0,
      "skill_teamGaugeGain": 6,
      "skill_allowed_types": [
        "burning",
        "blaze_attach",
        "blaze_burst",
        "magma_1",
        "magma_2",
        "magma_3",
        "magma_4"
      ],
      "skill_anomalies": [
        [
          {
            "type": "magma_1",
            "stacks": 1,
            "duration": 0
          }
        ]
      ],
      "link_duration": 1.7,
      "link_cooldown": 10,
      "link_spGain": 0,
      "link_gaugeGain": 0,
      "link_allowed_types": [
        "magma_1",
        "magma_2",
        "magma_3",
        "magma_4"
      ],
      "link_anomalies": [
        [
          {
            "type": "magma_1",
            "stacks": 1,
            "duration": 0
          }
        ]
      ],
      "ultimate_duration": 0.5,
      "ultimate_gaugeMax": 300,
      "ultimate_spGain": 0,
      "ultimate_gaugeReply": 0,
      "ultimate_allowed_types": [
        "magma_1",
        "magma_2",
        "magma_3",
        "magma_4",
        "blaze_attach",
        "burning",
        "blaze_burst"
      ],
      "ultimate_anomalies": [
        [
          {
            "type": "magma_1",
            "stacks": 1,
            "duration": 3.5
          },
          {
            "type": "magma_2",
            "stacks": 1,
            "duration": 3.5
          },
          {
            "type": "magma_3",
            "stacks": 1,
            "duration": 3.5
          },
          {
            "type": "magma_4",
            "stacks": 1,
            "duration": 0
          }
        ]
      ],
      "execution_duration": 1.5,
      "execution_spGain": 20,
      "execution_allowed_types": [
        "magma_1",
        "magma_2",
        "magma_3",
        "magma_4",
        "default",
        "conductive",
        "emag_attach",
        "emag_burst",
        "nature_attach",
        "corrosion",
        "nature_burst",
        "blaze_burst",
        "burning",
        "blaze_attach",
        "knockdown",
        "break",
        "ice_shatter",
        "knockup",
        "cold_attach",
        "frozen",
        "cold_burst",
        "stagger",
        "armor_break"
      ],
      "execution_anomalies": [],
      "accept_team_gauge": true,
      "attack_stagger": 18,
      "skill_anomaly_delays": [
        0.7
      ],
      "link_anomaly_delays": [
        1.3
      ],
      "ultimate_anomaly_delays": [
        3.5
      ]
    },
    {
      "id": "LIFENG",
      "name": "黎风",
      "rarity": 6,
      "element": "physical",
      "avatar": "/Endaxis/avatars/LIFENG.png",
      "exclusive_buffs": [
        {
          "key": "combo",
          "name": "连击",
          "path": "/Endaxis/icons/combo.png"
        },
        {
          "key": "physical_weakness",
          "name": "物理易伤",
          "path": "/Endaxis/icons/physical_weakness.png"
        }
      ],
      "attack_duration": 3.2,
      "attack_spGain": 21,
      "attack_allowed_types": [
        "break",
        "armor_break",
        "stagger",
        "knockdown",
        "knockup",
        "blaze_attach",
        "emag_attach",
        "cold_attach",
        "nature_attach",
        "blaze_burst",
        "emag_burst",
        "cold_burst",
        "nature_burst",
        "burning",
        "conductive",
        "frozen",
        "ice_shatter",
        "corrosion",
        "default"
      ],
      "attack_anomalies": [],
      "skill_duration": 2.2,
      "skill_spCost": 100,
      "skill_spGain": 0,
      "skill_gaugeGain": 0,
      "skill_teamGaugeGain": 0,
      "skill_allowed_types": [
        "knockdown",
        "break",
        "ice_shatter",
        "physical_weakness"
      ],
      "skill_anomalies": [
        [
          {
            "type": "knockdown",
            "stacks": 1,
            "duration": 0,
            "sp": 0,
            "stagger": 0
          },
          {
            "type": "physical_weakness",
            "stacks": 1,
            "duration": 10,
            "sp": 0,
            "stagger": 0
          }
        ]
      ],
      "link_duration": 2,
      "link_cooldown": 16,
      "link_spGain": 0,
      "link_gaugeGain": 10,
      "link_allowed_types": [
        "combo"
      ],
      "link_anomalies": [
        [
          {
            "type": "combo",
            "stacks": 1,
            "duration": 20,
            "sp": 0,
            "stagger": 0
          }
        ]
      ],
      "ultimate_duration": 0.5,
      "ultimate_gaugeMax": 90,
      "ultimate_spGain": 0,
      "ultimate_gaugeReply": 0,
      "ultimate_allowed_types": [
        "knockdown",
        "break",
        "ice_shatter"
      ],
      "ultimate_anomalies": [
        [
          {
            "type": "knockdown",
            "stacks": 1,
            "duration": 2,
            "stagger": 5,
            "sp": 0
          },
          {
            "type": "knockdown",
            "stacks": 1,
            "duration": 1.9,
            "stagger": 5,
            "sp": 0
          }
        ]
      ],
      "execution_duration": 1.5,
      "execution_spGain": 20,
      "execution_allowed_types": [
        "break",
        "armor_break",
        "stagger",
        "knockdown",
        "knockup",
        "blaze_attach",
        "emag_attach",
        "cold_attach",
        "nature_attach",
        "blaze_burst",
        "emag_burst",
        "cold_burst",
        "nature_burst",
        "burning",
        "conductive",
        "frozen",
        "ice_shatter",
        "corrosion",
        "default"
      ],
      "execution_anomalies": [],
      "accept_team_gauge": true,
      "attack_stagger": 19,
      "skill_anomaly_delays": [
        1.9
      ],
      "link_anomaly_delays": [
        0.7
      ],
      "skill_stagger": 10,
      "link_stagger": 10,
      "ultimate_stagger": 0,
      "variants": [
        {
          "id": "LIFENG_ultimate",
          "name": "强化终结技",
          "type": "ultimate",
          "duration": 0.5,
          "stagger": 0,
          "spGain": 0,
          "allowedTypes": [
            "knockdown",
            "break",
            "ice_shatter"
          ],
          "physicalAnomaly": [
            [
              {
                "type": "knockdown",
                "stacks": 1,
                "duration": 2,
                "stagger": 5,
                "sp": 0
              },
              {
                "type": "knockdown",
                "stacks": 1,
                "duration": 1.9,
                "stagger": 5,
                "sp": 0
              },
              {
                "type": "knockdown",
                "stacks": 1,
                "duration": 0,
                "stagger": 5,
                "sp": 0
              }
            ]
          ],
          "anomalyRowDelays": [],
          "gaugeCost": 90,
          "gaugeGain": 0
        }
      ]
    },
    {
      "id": "EMBER",
      "name": "余烬",
      "rarity": 6,
      "element": "blaze",
      "avatar": "/Endaxis/avatars/EMBER.png",
      "exclusive_buffs": [],
      "attack_duration": 4.2,
      "attack_spGain": 15,
      "attack_allowed_types": [
        "break",
        "armor_break",
        "stagger",
        "knockdown",
        "knockup",
        "blaze_attach",
        "emag_attach",
        "cold_attach",
        "nature_attach",
        "blaze_burst",
        "emag_burst",
        "cold_burst",
        "nature_burst",
        "burning",
        "conductive",
        "frozen",
        "ice_shatter",
        "corrosion",
        "default"
      ],
      "attack_anomalies": [],
      "skill_duration": 2,
      "skill_spCost": 100,
      "skill_spGain": 0,
      "skill_gaugeGain": 0,
      "skill_teamGaugeGain": 6,
      "skill_allowed_types": [
        "knockdown",
        "break",
        "ice_shatter"
      ],
      "skill_anomalies": [
        [
          {
            "type": "knockdown",
            "stacks": 1,
            "duration": 0
          }
        ]
      ],
      "link_duration": 1.1,
      "link_cooldown": 19,
      "link_spGain": 0,
      "link_gaugeGain": 0,
      "link_allowed_types": [
        "knockdown",
        "break",
        "ice_shatter"
      ],
      "link_anomalies": [
        [
          {
            "type": "knockdown",
            "stacks": 1,
            "duration": 0
          }
        ]
      ],
      "ultimate_duration": 0.5,
      "ultimate_gaugeMax": 100,
      "ultimate_spGain": 0,
      "ultimate_gaugeReply": 0,
      "ultimate_allowed_types": [
        "default"
      ],
      "ultimate_anomalies": [],
      "execution_duration": 1.5,
      "execution_spGain": 20,
      "execution_allowed_types": [
        "break",
        "armor_break",
        "stagger",
        "knockdown",
        "knockup",
        "blaze_attach",
        "emag_attach",
        "cold_attach",
        "nature_attach",
        "blaze_burst",
        "emag_burst",
        "cold_burst",
        "nature_burst",
        "burning",
        "conductive",
        "frozen",
        "ice_shatter",
        "corrosion",
        "default"
      ],
      "execution_anomalies": [],
      "accept_team_gauge": true,
      "attack_stagger": 25,
      "skill_anomaly_delays": [
        1.6
      ],
      "link_anomaly_delays": [
        0.9
      ]
    },
    {
      "id": "XAIHI",
      "name": "赛希",
      "rarity": 5,
      "element": "cold",
      "avatar": "/Endaxis/avatars/XAIHI.png",
      "exclusive_buffs": [],
      "accept_team_gauge": true,
      "attack_duration": 3.3,
      "attack_spGain": 15,
      "attack_stagger": 15,
      "attack_allowed_types": [
        "break",
        "armor_break",
        "stagger",
        "knockdown",
        "knockup",
        "blaze_attach",
        "emag_attach",
        "cold_attach",
        "nature_attach",
        "blaze_burst",
        "emag_burst",
        "cold_burst",
        "nature_burst",
        "burning",
        "conductive",
        "frozen",
        "ice_shatter",
        "corrosion",
        "default"
      ],
      "attack_anomalies": [],
      "skill_duration": 0.5,
      "skill_spCost": 100,
      "skill_spGain": 0,
      "skill_stagger": 0,
      "skill_gaugeGain": 0,
      "skill_teamGaugeGain": 6,
      "skill_allowed_types": [],
      "skill_anomalies": [],
      "link_duration": 1.2,
      "link_cooldown": 8,
      "link_spGain": 0,
      "link_stagger": 0,
      "link_gaugeGain": 0,
      "link_allowed_types": [
        "cold_attach",
        "frozen",
        "cold_burst"
      ],
      "link_anomalies": [
        [
          {
            "type": "cold_attach",
            "stacks": 1,
            "duration": 0
          }
        ]
      ],
      "ultimate_duration": 0.5,
      "ultimate_gaugeMax": 80,
      "ultimate_spGain": 0,
      "ultimate_stagger": 0,
      "ultimate_gaugeReply": 0,
      "ultimate_allowed_types": [],
      "ultimate_anomalies": [],
      "execution_duration": 1.5,
      "execution_spGain": 20,
      "execution_allowed_types": [
        "break",
        "armor_break",
        "stagger",
        "knockdown",
        "knockup",
        "blaze_attach",
        "emag_attach",
        "cold_attach",
        "nature_attach",
        "blaze_burst",
        "emag_burst",
        "cold_burst",
        "nature_burst",
        "burning",
        "conductive",
        "frozen",
        "ice_shatter",
        "corrosion",
        "default"
      ],
      "execution_anomalies": [],
      "link_anomaly_delays": [
        1
      ]
    },
    {
      "id": "SNOWSHINE",
      "name": "昼雪",
      "rarity": 5,
      "element": "cold",
      "avatar": "/Endaxis/avatars/SNOWSHINE.png",
      "exclusive_buffs": [],
      "accept_team_gauge": true,
      "attack_duration": 3.8,
      "attack_spGain": 15,
      "attack_stagger": 23,
      "attack_allowed_types": [
        "break",
        "armor_break",
        "stagger",
        "knockdown",
        "knockup",
        "blaze_attach",
        "emag_attach",
        "cold_attach",
        "nature_attach",
        "blaze_burst",
        "emag_burst",
        "cold_burst",
        "nature_burst",
        "burning",
        "conductive",
        "frozen",
        "ice_shatter",
        "corrosion",
        "default"
      ],
      "attack_anomalies": [],
      "skill_duration": 0.5,
      "skill_spCost": 100,
      "skill_spGain": 35,
      "skill_stagger": 0,
      "skill_gaugeGain": 0,
      "skill_teamGaugeGain": 6,
      "skill_allowed_types": [
        "cold_attach",
        "frozen",
        "cold_burst"
      ],
      "skill_anomalies": [],
      "link_duration": 1,
      "link_cooldown": 25,
      "link_spGain": 0,
      "link_stagger": 0,
      "link_gaugeGain": 0,
      "link_allowed_types": [],
      "link_anomalies": [],
      "ultimate_duration": 0.5,
      "ultimate_gaugeMax": 80,
      "ultimate_spGain": 0,
      "ultimate_stagger": 0,
      "ultimate_gaugeReply": 0,
      "ultimate_allowed_types": [
        "frozen",
        "cold_attach",
        "cold_burst",
        "default"
      ],
      "ultimate_anomalies": [
        [
          {
            "type": "frozen",
            "stacks": 1,
            "duration": 0
          }
        ]
      ],
      "execution_duration": 1.5,
      "execution_spGain": 20,
      "execution_allowed_types": [
        "break",
        "armor_break",
        "stagger",
        "knockdown",
        "knockup",
        "blaze_attach",
        "emag_attach",
        "cold_attach",
        "nature_attach",
        "blaze_burst",
        "emag_burst",
        "cold_burst",
        "nature_burst",
        "burning",
        "conductive",
        "frozen",
        "ice_shatter",
        "corrosion",
        "default"
      ],
      "execution_anomalies": [],
      "ultimate_anomaly_delays": [
        2
      ]
    },
    {
      "id": "ARCLIGHT",
      "name": "弧光",
      "rarity": 5,
      "element": "emag",
      "avatar": "/Endaxis/avatars/ARCLIGHT.png",
      "exclusive_buffs": [],
      "accept_team_gauge": true,
      "attack_duration": 3,
      "attack_spGain": 15,
      "attack_stagger": 16,
      "attack_allowed_types": [
        "break",
        "armor_break",
        "stagger",
        "knockdown",
        "knockup",
        "blaze_attach",
        "emag_attach",
        "cold_attach",
        "nature_attach",
        "blaze_burst",
        "emag_burst",
        "cold_burst",
        "nature_burst",
        "burning",
        "conductive",
        "frozen",
        "ice_shatter",
        "corrosion",
        "default"
      ],
      "attack_anomalies": [],
      "skill_duration": 1,
      "skill_spCost": 100,
      "skill_spGain": 0,
      "skill_stagger": 0,
      "skill_gaugeGain": 0,
      "skill_teamGaugeGain": 6,
      "skill_allowed_types": [],
      "skill_anomalies": [],
      "link_duration": 1,
      "link_cooldown": 3,
      "link_spGain": 0,
      "link_stagger": 0,
      "link_gaugeGain": 0,
      "link_allowed_types": [],
      "link_anomalies": [],
      "ultimate_duration": 0.5,
      "ultimate_gaugeMax": 90,
      "ultimate_spGain": 0,
      "ultimate_stagger": 0,
      "ultimate_gaugeReply": 0,
      "ultimate_allowed_types": [
        "emag_attach",
        "conductive",
        "emag_burst"
      ],
      "ultimate_anomalies": [
        [
          {
            "type": "emag_attach",
            "stacks": 1,
            "duration": 1.7
          },
          {
            "type": "conductive",
            "stacks": 1,
            "duration": 0
          }
        ]
      ],
      "execution_duration": 1.5,
      "execution_spGain": 20,
      "execution_allowed_types": [
        "break",
        "armor_break",
        "stagger",
        "knockdown",
        "knockup",
        "blaze_attach",
        "emag_attach",
        "cold_attach",
        "nature_attach",
        "blaze_burst",
        "emag_burst",
        "cold_burst",
        "nature_burst",
        "burning",
        "conductive",
        "frozen",
        "ice_shatter",
        "corrosion",
        "default"
      ],
      "execution_anomalies": []
    },
    {
      "id": "AVYWENNA",
      "name": "艾维文娜",
      "rarity": 5,
      "element": "emag",
      "avatar": "/Endaxis/avatars/AVYWENNA.png",
      "exclusive_buffs": [],
      "accept_team_gauge": true,
      "attack_duration": 3.2,
      "attack_spGain": 15,
      "attack_stagger": 17,
      "attack_allowed_types": [
        "break",
        "armor_break",
        "stagger",
        "knockdown",
        "knockup",
        "blaze_attach",
        "emag_attach",
        "cold_attach",
        "nature_attach",
        "blaze_burst",
        "emag_burst",
        "cold_burst",
        "nature_burst",
        "burning",
        "conductive",
        "frozen",
        "ice_shatter",
        "corrosion",
        "default"
      ],
      "attack_anomalies": [],
      "skill_duration": 0.5,
      "skill_spCost": 100,
      "skill_spGain": 0,
      "skill_stagger": 0,
      "skill_gaugeGain": 0,
      "skill_teamGaugeGain": 6,
      "skill_allowed_types": [
        "emag_burst",
        "conductive",
        "emag_attach"
      ],
      "skill_anomalies": [],
      "link_duration": 2.5,
      "link_cooldown": 13,
      "link_spGain": 0,
      "link_stagger": 0,
      "link_gaugeGain": 0,
      "link_allowed_types": [],
      "link_anomalies": [],
      "ultimate_duration": 0.5,
      "ultimate_gaugeMax": 100,
      "ultimate_spGain": 0,
      "ultimate_stagger": 0,
      "ultimate_gaugeReply": 0,
      "ultimate_allowed_types": [
        "default"
      ],
      "ultimate_anomalies": [
        [
          {
            "type": "default",
            "stacks": 1,
            "duration": 0
          }
        ]
      ],
      "execution_duration": 1.5,
      "execution_spGain": 20,
      "execution_allowed_types": [
        "break",
        "armor_break",
        "stagger",
        "knockdown",
        "knockup",
        "blaze_attach",
        "emag_attach",
        "cold_attach",
        "nature_attach",
        "blaze_burst",
        "emag_burst",
        "cold_burst",
        "nature_burst",
        "burning",
        "conductive",
        "frozen",
        "ice_shatter",
        "corrosion",
        "default"
      ],
      "execution_anomalies": []
    },
    {
      "id": "DAPAN",
      "name": "大潘",
      "rarity": 5,
      "element": "physical",
      "avatar": "/Endaxis/avatars/DAPAN.png",
      "exclusive_buffs": [
        {
          "key": "prep_ingredients",
          "name": "备料",
          "path": "/Endaxis/icons/prep_ingredients.png"
        }
      ],
      "accept_team_gauge": true,
      "attack_duration": 3.5,
      "attack_spGain": 21,
      "attack_stagger": 20,
      "attack_allowed_types": [
        "break",
        "armor_break",
        "stagger",
        "knockdown",
        "knockup",
        "blaze_attach",
        "emag_attach",
        "cold_attach",
        "nature_attach",
        "blaze_burst",
        "emag_burst",
        "cold_burst",
        "nature_burst",
        "burning",
        "conductive",
        "frozen",
        "ice_shatter",
        "corrosion",
        "default"
      ],
      "attack_anomalies": [],
      "skill_duration": 1.8,
      "skill_spCost": 100,
      "skill_spGain": 0,
      "skill_stagger": 0,
      "skill_gaugeGain": 0,
      "skill_teamGaugeGain": 0,
      "skill_allowed_types": [
        "knockup",
        "break",
        "ice_shatter"
      ],
      "skill_anomalies": [
        [
          {
            "type": "knockup",
            "stacks": 2,
            "duration": 0,
            "stagger": 10
          }
        ]
      ],
      "link_duration": 2.1,
      "link_cooldown": 20,
      "link_spGain": 0,
      "link_stagger": 0,
      "link_gaugeGain": 10,
      "link_allowed_types": [
        "stagger",
        "break",
        "ice_shatter"
      ],
      "link_anomalies": [
        [
          {
            "type": "stagger",
            "stacks": 4,
            "duration": 0,
            "sp": 0,
            "stagger": 15
          }
        ]
      ],
      "ultimate_duration": 0.5,
      "ultimate_gaugeMax": 90,
      "ultimate_spGain": 0,
      "ultimate_stagger": 0,
      "ultimate_gaugeReply": 0,
      "ultimate_allowed_types": [
        "knockdown",
        "break",
        "ice_shatter",
        "knockup",
        "prep_ingredients"
      ],
      "ultimate_anomalies": [
        [
          {
            "type": "knockup",
            "stacks": 1,
            "duration": 1.1,
            "sp": 0,
            "stagger": 0
          },
          {
            "type": "knockdown",
            "stacks": 1,
            "duration": 0,
            "sp": 0,
            "stagger": 0
          }
        ],
        [
          {
            "type": "prep_ingredients",
            "stacks": 1,
            "duration": 0,
            "sp": 0,
            "stagger": 0
          }
        ]
      ],
      "execution_duration": 1.5,
      "execution_spGain": 20,
      "execution_allowed_types": [
        "break",
        "armor_break",
        "stagger",
        "knockdown",
        "knockup",
        "blaze_attach",
        "emag_attach",
        "cold_attach",
        "nature_attach",
        "blaze_burst",
        "emag_burst",
        "cold_burst",
        "nature_burst",
        "burning",
        "conductive",
        "frozen",
        "ice_shatter",
        "corrosion",
        "default"
      ],
      "execution_anomalies": [],
      "skill_anomaly_delays": [
        1.5
      ],
      "variants": [
        {
          "id": "DAPAN_link",
          "name": "强化连携",
          "type": "link",
          "duration": 2.1,
          "stagger": 0,
          "spGain": 0,
          "allowedTypes": [
            "stagger",
            "break",
            "ice_shatter"
          ],
          "physicalAnomaly": [
            [
              {
                "type": "stagger",
                "stacks": 4,
                "duration": 0,
                "sp": 0,
                "stagger": 15
              }
            ]
          ],
          "anomalyRowDelays": [],
          "cooldown": 12,
          "gaugeGain": 10
        }
      ]
    },
    {
      "id": "WULFGARD",
      "name": "狼卫",
      "rarity": 5,
      "element": "blaze",
      "avatar": "/Endaxis/avatars/WULFGARD.png",
      "exclusive_buffs": [],
      "accept_team_gauge": true,
      "attack_duration": 4,
      "attack_spGain": 15,
      "attack_stagger": 18,
      "attack_allowed_types": [
        "break",
        "armor_break",
        "stagger",
        "knockdown",
        "knockup",
        "blaze_attach",
        "emag_attach",
        "cold_attach",
        "nature_attach",
        "blaze_burst",
        "emag_burst",
        "cold_burst",
        "nature_burst",
        "burning",
        "conductive",
        "frozen",
        "ice_shatter",
        "corrosion",
        "default"
      ],
      "attack_anomalies": [],
      "skill_duration": 1.2,
      "skill_spCost": 100,
      "skill_spGain": 0,
      "skill_stagger": 0,
      "skill_gaugeGain": 0,
      "skill_teamGaugeGain": 6,
      "skill_allowed_types": [
        "blaze_attach",
        "burning",
        "blaze_burst"
      ],
      "skill_anomalies": [
        [
          {
            "type": "blaze_attach",
            "stacks": 1,
            "duration": 0
          }
        ]
      ],
      "link_duration": 1.2,
      "link_cooldown": 20,
      "link_spGain": 0,
      "link_stagger": 0,
      "link_gaugeGain": 0,
      "link_allowed_types": [
        "blaze_attach",
        "burning",
        "blaze_burst"
      ],
      "link_anomalies": [
        [
          {
            "type": "blaze_attach",
            "stacks": 1,
            "duration": 0
          }
        ]
      ],
      "ultimate_duration": 0.5,
      "ultimate_gaugeMax": 90,
      "ultimate_spGain": 0,
      "ultimate_stagger": 0,
      "ultimate_gaugeReply": 0,
      "ultimate_allowed_types": [
        "burning",
        "blaze_attach",
        "blaze_burst"
      ],
      "ultimate_anomalies": [
        [
          {
            "type": "burning",
            "stacks": 1,
            "duration": 0
          }
        ]
      ],
      "execution_duration": 1.5,
      "execution_spGain": 20,
      "execution_allowed_types": [
        "break",
        "armor_break",
        "stagger",
        "knockdown",
        "knockup",
        "blaze_attach",
        "emag_attach",
        "cold_attach",
        "nature_attach",
        "blaze_burst",
        "emag_burst",
        "cold_burst",
        "nature_burst",
        "burning",
        "conductive",
        "frozen",
        "ice_shatter",
        "corrosion",
        "default"
      ],
      "execution_anomalies": [],
      "skill_anomaly_delays": [
        0.9
      ],
      "link_anomaly_delays": [
        0.9
      ]
    },
    {
      "id": "PERLICA",
      "name": "佩丽卡",
      "rarity": 5,
      "element": "emag",
      "avatar": "/Endaxis/avatars/PERLICA.png",
      "exclusive_buffs": [],
      "accept_team_gauge": true,
      "attack_duration": 3.3,
      "attack_spGain": 15,
      "attack_stagger": 15,
      "attack_allowed_types": [
        "break",
        "armor_break",
        "stagger",
        "knockdown",
        "knockup",
        "blaze_attach",
        "emag_attach",
        "cold_attach",
        "nature_attach",
        "blaze_burst",
        "emag_burst",
        "cold_burst",
        "nature_burst",
        "burning",
        "conductive",
        "frozen",
        "ice_shatter",
        "corrosion",
        "default"
      ],
      "attack_anomalies": [],
      "skill_duration": 0.8,
      "skill_spCost": 100,
      "skill_spGain": 0,
      "skill_stagger": 0,
      "skill_gaugeGain": 0,
      "skill_teamGaugeGain": 6,
      "skill_allowed_types": [
        "emag_attach",
        "conductive",
        "emag_burst"
      ],
      "skill_anomalies": [
        [
          {
            "type": "emag_attach",
            "stacks": 1,
            "duration": 0
          }
        ]
      ],
      "link_duration": 1.2,
      "link_cooldown": 20,
      "link_spGain": 0,
      "link_stagger": 0,
      "link_gaugeGain": 0,
      "link_allowed_types": [
        "conductive",
        "emag_attach",
        "emag_burst"
      ],
      "link_anomalies": [
        [
          {
            "type": "conductive",
            "stacks": 1,
            "duration": 8.75
          }
        ]
      ],
      "ultimate_duration": 0.5,
      "ultimate_gaugeMax": 80,
      "ultimate_spGain": 0,
      "ultimate_stagger": 0,
      "ultimate_gaugeReply": 0,
      "ultimate_allowed_types": [],
      "ultimate_anomalies": [],
      "execution_duration": 1.5,
      "execution_spGain": 20,
      "execution_allowed_types": [
        "break",
        "armor_break",
        "stagger",
        "knockdown",
        "knockup",
        "blaze_attach",
        "emag_attach",
        "cold_attach",
        "nature_attach",
        "blaze_burst",
        "emag_burst",
        "cold_burst",
        "nature_burst",
        "burning",
        "conductive",
        "frozen",
        "ice_shatter",
        "corrosion",
        "default"
      ],
      "execution_anomalies": [],
      "skill_anomaly_delays": [
        0.5
      ],
      "link_anomaly_delays": [
        0.9
      ]
    },
    {
      "id": "CHENQIANYU",
      "name": "陈千语",
      "rarity": 5,
      "element": "physical",
      "avatar": "/Endaxis/avatars/CHENQIANYU.png",
      "exclusive_buffs": [],
      "attack_duration": 3.2,
      "attack_spGain": 18,
      "attack_allowed_types": [
        "default",
        "conductive",
        "emag_attach",
        "emag_burst",
        "burning",
        "blaze_attach",
        "blaze_burst",
        "knockup",
        "break",
        "ice_shatter",
        "nature_attach",
        "corrosion",
        "nature_burst",
        "knockdown",
        "cold_attach",
        "frozen",
        "cold_burst",
        "stagger",
        "armor_break"
      ],
      "attack_anomalies": [],
      "skill_duration": 0.8,
      "skill_spCost": 100,
      "skill_gaugeGain": 0,
      "skill_allowed_types": [
        "knockup",
        "break",
        "ice_shatter"
      ],
      "skill_anomalies": [
        [
          {
            "type": "knockup",
            "stacks": 2,
            "duration": 0,
            "stagger": 10,
            "sp": 0
          }
        ]
      ],
      "link_duration": 0.9,
      "link_cooldown": 16,
      "link_spGain": 0,
      "link_gaugeGain": 0,
      "link_allowed_types": [
        "knockup",
        "break",
        "ice_shatter"
      ],
      "link_anomalies": [
        [
          {
            "type": "knockup",
            "stacks": 2,
            "duration": 0,
            "sp": 10,
            "stagger": 10
          }
        ]
      ],
      "ultimate_duration": 0.5,
      "ultimate_gaugeMax": 70,
      "ultimate_gaugeReply": 0,
      "ultimate_allowed_types": [
        "default"
      ],
      "ultimate_anomalies": [
        [
          {
            "type": "default",
            "stacks": 1,
            "duration": 0,
            "sp": 0,
            "stagger": 15
          },
          {
            "type": "default",
            "stacks": 1,
            "duration": 0,
            "sp": 0,
            "stagger": 20
          }
        ]
      ],
      "execution_duration": 2.5,
      "execution_spGain": 30,
      "execution_allowed_types": [],
      "execution_anomalies": [],
      "skill_spGain": 0,
      "ultimate_spGain": 0,
      "skill_teamGaugeGain": 0,
      "attack_stagger": 16,
      "skill_stagger": 0,
      "link_stagger": 0,
      "accept_team_gauge": true,
      "skill_anomaly_delays": [
        0.5
      ],
      "link_anomaly_delays": [
        0.6
      ],
      "ultimate_stagger": 0
    },
    {
      "id": "ALESH",
      "name": "阿列什",
      "rarity": 5,
      "element": "cold",
      "avatar": "/Endaxis/avatars/ALESH.png",
      "exclusive_buffs": [],
      "attack_duration": 3.2,
      "attack_spGain": 10,
      "attack_allowed_types": [
        "corrosion",
        "nature_attach",
        "nature_burst",
        "burning",
        "blaze_attach",
        "blaze_burst",
        "conductive",
        "emag_attach",
        "emag_burst",
        "knockup",
        "break",
        "ice_shatter",
        "knockdown",
        "cold_attach",
        "frozen",
        "cold_burst",
        "stagger",
        "armor_break",
        "default"
      ],
      "attack_anomalies": [],
      "skill_duration": 1.3,
      "skill_spCost": 100,
      "skill_gaugeGain": 17,
      "skill_allowed_types": [
        "frozen",
        "cold_attach",
        "cold_burst"
      ],
      "skill_anomalies": [
        [
          {
            "type": "frozen",
            "stacks": 1,
            "duration": 5
          }
        ]
      ],
      "link_duration": 1.5,
      "link_cooldown": 9,
      "link_spGain": 10,
      "link_gaugeGain": 10,
      "link_allowed_types": [
        "default"
      ],
      "link_anomalies": [],
      "ultimate_duration": 0.5,
      "ultimate_gaugeMax": 100,
      "ultimate_gaugeReply": 0,
      "ultimate_allowed_types": [
        "cold_burst",
        "frozen",
        "cold_attach"
      ],
      "ultimate_anomalies": [
        [
          {
            "type": "cold_attach",
            "stacks": 1,
            "duration": 0
          }
        ]
      ],
      "execution_duration": 1.5,
      "execution_spGain": 20,
      "execution_allowed_types": [],
      "execution_anomalies": [],
      "skill_spGain": 30,
      "ultimate_spGain": 30,
      "skill_teamGaugeGain": 6,
      "skill_stagger": 12,
      "link_stagger": 12,
      "accept_team_gauge": true,
      "attack_stagger": 17,
      "skill_anomaly_delays": [
        1
      ]
    },
    {
      "id": "CATCHER",
      "name": "卡契尔",
      "rarity": 4,
      "element": "physical",
      "avatar": "/Endaxis/avatars/CATCHER.png",
      "exclusive_buffs": [],
      "accept_team_gauge": true,
      "attack_duration": 2.5,
      "attack_spGain": 15,
      "attack_stagger": 22,
      "attack_allowed_types": [
        "break",
        "armor_break",
        "stagger",
        "knockdown",
        "knockup",
        "blaze_attach",
        "emag_attach",
        "cold_attach",
        "nature_attach",
        "blaze_burst",
        "emag_burst",
        "cold_burst",
        "nature_burst",
        "burning",
        "conductive",
        "frozen",
        "ice_shatter",
        "corrosion",
        "default"
      ],
      "attack_anomalies": [],
      "skill_duration": 2,
      "skill_spCost": 100,
      "skill_spGain": 0,
      "skill_stagger": 0,
      "skill_gaugeGain": 0,
      "skill_teamGaugeGain": 6,
      "skill_allowed_types": [],
      "skill_anomalies": [],
      "link_duration": 1.5,
      "link_cooldown": 15,
      "link_spGain": 0,
      "link_stagger": 0,
      "link_gaugeGain": 0,
      "link_allowed_types": [],
      "link_anomalies": [],
      "ultimate_duration": 3,
      "ultimate_gaugeMax": 100,
      "ultimate_spGain": 0,
      "ultimate_stagger": 0,
      "ultimate_gaugeReply": 0,
      "ultimate_allowed_types": [],
      "ultimate_anomalies": [],
      "execution_duration": 1.5,
      "execution_spGain": 20,
      "execution_allowed_types": [
        "break",
        "armor_break",
        "stagger",
        "knockdown",
        "knockup",
        "blaze_attach",
        "emag_attach",
        "cold_attach",
        "nature_attach",
        "blaze_burst",
        "emag_burst",
        "cold_burst",
        "nature_burst",
        "burning",
        "conductive",
        "frozen",
        "ice_shatter",
        "corrosion",
        "default"
      ],
      "execution_anomalies": []
    },
    {
      "id": "FLUORITE",
      "name": "萤石",
      "rarity": 4,
      "element": "nature",
      "avatar": "/Endaxis/avatars/FLUORITE.png",
      "exclusive_buffs": [],
      "accept_team_gauge": true,
      "attack_duration": 2.5,
      "attack_spGain": 15,
      "attack_stagger": 15,
      "attack_allowed_types": [
        "break",
        "armor_break",
        "stagger",
        "knockdown",
        "knockup",
        "blaze_attach",
        "emag_attach",
        "cold_attach",
        "nature_attach",
        "blaze_burst",
        "emag_burst",
        "cold_burst",
        "nature_burst",
        "burning",
        "conductive",
        "frozen",
        "ice_shatter",
        "corrosion",
        "default"
      ],
      "attack_anomalies": [],
      "skill_duration": 2,
      "skill_spCost": 100,
      "skill_spGain": 0,
      "skill_stagger": 0,
      "skill_gaugeGain": 0,
      "skill_teamGaugeGain": 6,
      "skill_allowed_types": [],
      "skill_anomalies": [],
      "link_duration": 1.5,
      "link_cooldown": 15,
      "link_spGain": 0,
      "link_stagger": 0,
      "link_gaugeGain": 0,
      "link_allowed_types": [],
      "link_anomalies": [],
      "ultimate_duration": 3,
      "ultimate_gaugeMax": 100,
      "ultimate_spGain": 0,
      "ultimate_stagger": 0,
      "ultimate_gaugeReply": 0,
      "ultimate_allowed_types": [],
      "ultimate_anomalies": [],
      "execution_duration": 1.5,
      "execution_spGain": 20,
      "execution_allowed_types": [
        "break",
        "armor_break",
        "stagger",
        "knockdown",
        "knockup",
        "blaze_attach",
        "emag_attach",
        "cold_attach",
        "nature_attach",
        "blaze_burst",
        "emag_burst",
        "cold_burst",
        "nature_burst",
        "burning",
        "conductive",
        "frozen",
        "ice_shatter",
        "corrosion",
        "default"
      ],
      "execution_anomalies": []
    },
    {
      "id": "ANTAL",
      "name": "安塔尔",
      "rarity": 4,
      "element": "emag",
      "avatar": "/Endaxis/avatars/ANTAL.png",
      "exclusive_buffs": [],
      "accept_team_gauge": true,
      "attack_duration": 2.5,
      "attack_spGain": 15,
      "attack_stagger": 15,
      "attack_allowed_types": [
        "break",
        "armor_break",
        "stagger",
        "knockdown",
        "knockup",
        "blaze_attach",
        "emag_attach",
        "cold_attach",
        "nature_attach",
        "blaze_burst",
        "emag_burst",
        "cold_burst",
        "nature_burst",
        "burning",
        "conductive",
        "frozen",
        "ice_shatter",
        "corrosion",
        "default"
      ],
      "attack_anomalies": [],
      "skill_duration": 2,
      "skill_spCost": 100,
      "skill_spGain": 0,
      "skill_stagger": 0,
      "skill_gaugeGain": 0,
      "skill_teamGaugeGain": 6,
      "skill_allowed_types": [],
      "skill_anomalies": [],
      "link_duration": 1.5,
      "link_cooldown": 15,
      "link_spGain": 0,
      "link_stagger": 0,
      "link_gaugeGain": 0,
      "link_allowed_types": [],
      "link_anomalies": [],
      "ultimate_duration": 3,
      "ultimate_gaugeMax": 100,
      "ultimate_spGain": 0,
      "ultimate_stagger": 0,
      "ultimate_gaugeReply": 0,
      "ultimate_allowed_types": [],
      "ultimate_anomalies": [],
      "execution_duration": 1.5,
      "execution_spGain": 20,
      "execution_allowed_types": [
        "break",
        "armor_break",
        "stagger",
        "knockdown",
        "knockup",
        "blaze_attach",
        "emag_attach",
        "cold_attach",
        "nature_attach",
        "blaze_burst",
        "emag_burst",
        "cold_burst",
        "nature_burst",
        "burning",
        "conductive",
        "frozen",
        "ice_shatter",
        "corrosion",
        "default"
      ],
      "execution_anomalies": []
    },
    {
      "id": "ESTELLA",
      "name": "埃特拉",
      "rarity": 4,
      "element": "cold",
      "avatar": "/Endaxis/avatars/ESTELLA.png",
      "exclusive_buffs": [],
      "attack_duration": 2.5,
      "attack_spGain": 15,
      "attack_allowed_types": [
        "corrosion",
        "nature_attach",
        "nature_burst",
        "burning",
        "blaze_attach",
        "blaze_burst",
        "conductive",
        "emag_attach",
        "emag_burst",
        "cold_attach",
        "frozen",
        "cold_burst",
        "knockdown",
        "break",
        "ice_shatter",
        "knockup",
        "stagger",
        "armor_break",
        "default"
      ],
      "attack_anomalies": [],
      "skill_duration": 2,
      "skill_spCost": 100,
      "skill_gaugeGain": 0,
      "skill_allowed_types": [
        "cold_burst",
        "frozen",
        "cold_attach"
      ],
      "skill_anomalies": [
        [
          {
            "type": "cold_attach",
            "stacks": 1,
            "duration": 0
          }
        ]
      ],
      "link_duration": 1.5,
      "link_cooldown": 15,
      "link_spGain": 0,
      "link_gaugeGain": 0,
      "link_allowed_types": [
        "knockup",
        "break",
        "ice_shatter"
      ],
      "link_anomalies": [
        [
          {
            "type": "knockup",
            "stacks": 1,
            "duration": 0
          },
          {
            "type": "ice_shatter",
            "stacks": 1,
            "duration": 0
          }
        ]
      ],
      "ultimate_duration": 3,
      "ultimate_gaugeMax": 100,
      "ultimate_gaugeReply": 0,
      "ultimate_allowed_types": [
        "default"
      ],
      "ultimate_anomalies": [],
      "execution_duration": 1.5,
      "execution_spGain": 20,
      "execution_allowed_types": [],
      "execution_anomalies": [],
      "ultimate_spGain": 0,
      "skill_spGain": 0,
      "skill_teamGaugeGain": 6,
      "skill_stagger": 12,
      "link_stagger": 24,
      "accept_team_gauge": true,
      "attack_stagger": 17
    },
    {
      "id": "AKEKURI",
      "name": "秋栗",
      "rarity": 4,
      "element": "blaze",
      "avatar": "/Endaxis/avatars/AKEKURI.png",
      "exclusive_buffs": [],
      "attack_duration": 2.5,
      "attack_spGain": 15,
      "attack_allowed_types": [
        "corrosion",
        "nature_attach",
        "nature_burst",
        "burning",
        "blaze_attach",
        "blaze_burst",
        "conductive",
        "emag_attach",
        "emag_burst",
        "cold_attach",
        "frozen",
        "cold_burst",
        "ice_shatter",
        "knockdown",
        "break",
        "knockup",
        "stagger",
        "armor_break",
        "default"
      ],
      "attack_anomalies": [],
      "skill_duration": 2,
      "skill_spCost": 100,
      "skill_gaugeGain": 0,
      "skill_allowed_types": [
        "blaze_attach",
        "burning",
        "blaze_burst"
      ],
      "skill_anomalies": [
        [
          {
            "type": "blaze_attach",
            "stacks": 1,
            "duration": 0
          }
        ]
      ],
      "link_duration": 1.5,
      "link_cooldown": 15,
      "link_spGain": 0,
      "link_gaugeGain": 0,
      "link_allowed_types": [
        "default"
      ],
      "link_anomalies": [],
      "ultimate_duration": 3,
      "ultimate_gaugeMax": 100,
      "ultimate_gaugeReply": 0,
      "ultimate_allowed_types": [
        "default"
      ],
      "ultimate_anomalies": [],
      "execution_duration": 1.5,
      "execution_spGain": 20,
      "execution_allowed_types": [],
      "execution_anomalies": [],
      "skill_spGain": 0,
      "ultimate_spGain": 0,
      "skill_teamGaugeGain": 6,
      "accept_team_gauge": true,
      "attack_stagger": 17
    }
  ]
}